{
    "yourprojectname": {
        "include": [
            "./res/htttp/include",
            "./bout/info/lo"
        ],
        "libs": [
            "curl",
            "grpa"
        ],
        "libsDir": [
            "../",
            "../../les"
        ],
        "compiler":"clang++"
    },
    "youranotherproject": {
        "include": [
            "./res/htttp/include/proj",
            "./bout/info/lo/g"
        ],
        "libs": [
            "grpasdf",
            "curl23"
        ],
        "libsDir": [
            "../../les/sda",
            "../../../sd"
        ],
        "compiler":"mingw"
    }
}